{
  "proName":"华为 HUAWEI Mate 10 6GB+128GB 亮黑色 移动联通电信4G手机 双卡双待",
  "proId":"00006",
  "proType":[
    {
      "proTypeName":"原装+套餐1",
      "proTypeNum":"111",
      "proPrice":"4499",
      "proColor":[
        "红色","黑色","紫色"
      ]
    },
    {
      "proTypeName":"原装+套餐2",
      "proTypeNum":"12321",
      "proPrice":"4499",
      "proColor":[
        "红色","绿色","黑色","紫色"
      ]
    },
    {
      "proTypeName":"原装+套餐3",
      "proTypeNum":"142111",
      "proPrice":"4499",
      "proColor":[
        "红色","绿色","黑色"
      ]
    },
    {
      "proTypeName":"原装+套餐4",
      "proTypeNum":"11331",
      "proPrice":"4499",
      "proColor":[
        "红色","绿色","紫色"
      ]
    }
  ],
  "proImg":[{
    "url": "javascript:",
    "img": "https://m.360buyimg.com/n12/jfs/t10177/326/1292333258/167702/38059e69/59ded62eN64a9784c.jpg!q70.jpg"
  }, {
    "url": "javascript:",
    "img": "https://m.360buyimg.com/n12/jfs/t9844/307/1289359815/109699/af156a8e/59ded626Ne3c69b70.jpg!q70.jpg"
  }, {
    "url": "javascript:",
    "img": "https://m.360buyimg.com/n12/s750x750_jfs/t10453/229/1275964920/106051/51e45710/59ded62dN7e28abc5.jpg!q70.jpg"
  },{
    "url": "javascript:",
    "img": "https://m.360buyimg.com/n12/s750x750_jfs/t9823/12/1280327871/26265/ddd69e27/59ded62dNfed003a8.jpg!q70.jpg"
  }],
  "proInforImg":[
    "https://img20.360buyimg.com/vc/jfs/t14242/208/2427881305/1019028/40ac73bc/5a9f8fa3N02dce840.jpg"
  ],
  "proTable":[{"辅助功能":[{"其他特性":"手套模式"},{"常用功能":"录音"},{"常用功能":"手势识别"},{"常用功能":"便签"},{"常用功能":"超大字体"},{"常用功能":"SOS功能"},{"常用功能":"重力感应"},{"其他1":"智能识屏"},{"其他2":"单手操作"}]},{"主体":[{"上市年份":"2017年"},{"品牌":"华为（HUAWEI）"},{"型号":"ALP-AL00"},{"上市月份":"10月"},{"入网型号":"ALP-AL00"}]},{"手机特性":[{"其他":"呼吸灯"},{"其他":"多麦降噪技术"},{"其他":"光线感应"},{"适配VR":"支持"},{"红外遥控":"支持"},{"陀螺仪":"支持"},{"霍尔感应器":"支持"},{"电子罗盘":"支持"},{"GPS":"支持"},{"语音识别":"支持"},{"指纹识别":"支持"}]},{"基本信息":[{"机身宽度（mm）":"77.8"},{"机身厚度（mm）":"8.2"},{"机身长度（mm）":"150.5"},{"运营商标志或内容":"无"},{"输入方式":"触控"},{"机身重量（g）":"约186g（含电池）"},{"机身材质工艺":"四曲面玻璃后壳"},{"机身颜色":"亮黑色"},{"机身材质分类":"金属边框"},{"机身材质分类":"玻璃后盖"}]},{"数据接口":[{"数据线":"其他"},{"充电接口类型":"Type-C"},{"耳机接口类型":"3.5mm"},{"数据传输接口":"红外"},{"数据传输接口":"WIFI"},{"数据传输接口":"NFC"},{"数据传输接口":"蓝牙"},{"数据传输接口":"WiFi热点"},{"NFC/NFC模式":"支持（点对点模式）"},{"NFC/NFC模式":"支持（读卡器模式）"},{"NFC/NFC模式":"支持卡模拟"}]},{"电池信息":[{"快速充电":"华为超级快充"},{"充电器":"5V/4.5A"},{"电池类型":"锂聚合物电池"},{"电池是否可拆卸":"否"},{"电池容量（mAh）":"4000（典型值) "}]},{"后置摄像头":[{"照片最大分辨率":"5120X3840"},{"拍照特点":"数码变焦"},{"拍照特点":"自动对焦"},{"拍照特点":"防抖"},{"拍照特点":"美颜"},{"拍照特点":"连拍"},{"拍照特点":"微距"},{"拍照特点":"全景"},{"拍照特点":"滤镜"},{"拍照特点":"场景模式"},{"拍照特点":"HDR"},{"拍照特点":"PDAF"},{"拍照特点":"夜间拍摄"},{"拍照特点":"微信小视频"},{"拍照特点":"有声照片"},{"拍照特点":"水印"},{"拍照特点":"美肤录像"},{"拍照特点":"全像素双核激光对焦拍摄"},{"美颜技术":"支持"},{"闪光灯":"双色温双LED闪光灯"},{"副摄像头光圈大小":"其他"},{"后置摄像头":"1200万像素"},{"后置摄像头":"2000万像素"},{"摄像头数量":"2个"},{"摄像头光圈大小":"其他"}]},{"前置摄像头":[{"前置摄像头":"800万像素"},{"前摄光圈大小":"f/2.0"},{"美颜技术":"支持"}]},{"娱乐功能":[{"mic数量":"3个"}]},{"存储":[{"最大存储扩展容量":"256GB"},{"存储卡":"支持MicroSD（TF）"},{"ROM":"128GB"},{"RAM":"6GB"}]},{"网络支持":[{"3G/2G网络":"3G：移动(TD-SCDMA)"},{"3G/2G网络":"3G：联通(WCDMA)"},{"3G/2G网络":"3G：电信(CDMA2000)"},{"3G/2G网络":"2G：移动联通(GSM)+电信(CDMA)"},{"4G网络":"4G：移动（TD-LTE)"},{"4G网络":"4G：联通(FDD-LTE)"},{"4G网络":"4G：电信(FDD-LTE)"},{"4G网络":"4G：联通(TD-LTE)"},{"副SIM卡类型":"副SIM卡与存储卡二选一"},{"副SIM卡4G网络":"4G：移动（TD-LTE)"},{"副SIM卡4G网络":"4G：联通(FDD-LTE)"},{"副SIM卡4G网络":"4G：电信(FDD-LTE)"},{"副SIM卡4G网络":"4G：联通(TD-LTE)"},{"副SIM卡3G/2G网络":"不支持主副卡同时使用电信卡"},{"副SIM卡3G/2G网络":"3G：联通(WCDMA)"},{"副SIM卡3G/2G网络":"3G：电信(CDMA2000)"},{"副SIM卡3G/2G网络":"2G：移动联通(GSM)+电信(CDMA)"},{"最大支持SIM卡数量":"2个"},{"双卡机类型":"双卡双待单通"},{"SIM卡类型":"Nano SIM"},{"网络频率（2G/3G）":"2G：GSM 850/900/1800/1900"},{"网络频率（2G/3G）":"2G：CDMA 800"},{"网络频率（2G/3G）":"3G：TD-SCDMA 1900/2000"},{"网络频率（2G/3G）":"3G：WCDMA 850/900/1900/2100"},{"网络频率（2G/3G）":"3G：CDMA2000"},{"网络频率（2G/3G）":"3G：CDMA 800MHz 1X&EVDO"},{"网络频率（2G/3G）":"3G：WCDMA：850/900/1700/1900/2100MHz"}]},{"主芯片":[{"CPU型号":"麒麟970"},{"CPU核数":"八核"},{"CPU品牌":"海思（Hisilicon）"},{"CPU频率":"4*Cortex A73 2.36GHz + 4*Cortex A53 1.8GHz"}]},{"操作系统":[{"操作系统版本":"华为 EMUI 8.0"},{"操作系统":"Android"}]},{"屏幕":[{"主屏幕尺寸（英寸）":"5.9英寸"},{"分辨率":"2560×1440（Quad HD / 2K ）"},{"屏幕材质类型":"TFT"}]}]
}
